CHANGELOG.md
MANIFEST.in
requirements.txt
setup.py
test/__init__.py
test/test_ml_toolkit.py
wedpr_ml_toolkit/__init__.py
wedpr_ml_toolkit/wedpr_ml_toolkit.py
wedpr_ml_toolkit.egg-info/PKG-INFO
wedpr_ml_toolkit.egg-info/SOURCES.txt
wedpr_ml_toolkit.egg-info/dependency_links.txt
wedpr_ml_toolkit.egg-info/requires.txt
wedpr_ml_toolkit.egg-info/top_level.txt
wedpr_ml_toolkit/common/__init__.py
wedpr_ml_toolkit/common/utils/__init__.py
wedpr_ml_toolkit/common/utils/base_object.py
wedpr_ml_toolkit/common/utils/constant.py
wedpr_ml_toolkit/common/utils/hdfs_storage_impl.py
wedpr_ml_toolkit/common/utils/properies_parser.py
wedpr_ml_toolkit/common/utils/utils.py
wedpr_ml_toolkit/config/__init__.py
wedpr_ml_toolkit/config/wedpr_ml_config.py
wedpr_ml_toolkit/context/__init__.py
wedpr_ml_toolkit/context/data_context.py
wedpr_ml_toolkit/context/dataset_context.py
wedpr_ml_toolkit/context/job_context.py
wedpr_ml_toolkit/context/model_setting.py
wedpr_ml_toolkit/context/result/__init__.py
wedpr_ml_toolkit/context/result/fe_result_context.py
wedpr_ml_toolkit/context/result/model_result_context.py
wedpr_ml_toolkit/context/result/psi_result_context.py
wedpr_ml_toolkit/context/result/result_context.py
wedpr_ml_toolkit/transport/__init__.py
wedpr_ml_toolkit/transport/credential_generator.py
wedpr_ml_toolkit/transport/storage_entrypoint.py
wedpr_ml_toolkit/transport/wedpr_entrypoint.py
wedpr_ml_toolkit/transport/wedpr_remote_dataset_client.py
wedpr_ml_toolkit/transport/wedpr_remote_job_client.py